{
  "noiseKey": {
    "private": {
      "type": "Buffer",
      "data": "oNhzOybwuxyA2q/wXNvMSIa5Te2ZWAtGrvCaGUnVkE4="
    },
    "public": {
      "type": "Buffer",
      "data": "AP56aLFJEzm8GRUcvZPyl7jgqIlJTzoTsOctMIlO8D4="
    }
  },
  "pairingEphemeralKeyPair": {
    "private": {
      "type": "Buffer",
      "data": "mMX6j+fh5ftsebNFItkEmvlKcd8w5CQ3mNAYDMffFkU="
    },
    "public": {
      "type": "Buffer",
      "data": "WaWzLUxth2n2cDyUxO0QGpDFzCyAbbljDm18TAiVH1Q="
    }
  },
  "signedIdentityKey": {
    "private": {
      "type": "Buffer",
      "data": "uBqoM0Upsc9mvfsYL1RkbBBZcYplNyFB5kujGGnKyGw="
    },
    "public": {
      "type": "Buffer",
      "data": "9d3t2ZiJFS4o1fWFHNfHgF/cA6bSg2LGFUJkv2jOGSw="
    }
  },
  "signedPreKey": {
    "keyPair": {
      "private": {
        "type": "Buffer",
        "data": "iPsi8DE7K+9fE4nVt7k6obJDs24UhsqhL5Sp11RrSXo="
      },
      "public": {
        "type": "Buffer",
        "data": "QVDs5wviJyH7/0xfHzxIXgyzzaYvxLV1zgDYJqHBQiU="
      }
    },
    "signature": {
      "type": "Buffer",
      "data": "TdkyFU3DMGdN/YtD375233r8lRNe+DIg09ao35ECWS+LLWT79BmuAcz0HZJXj1RPxMulYM6ato0xczx5uOJTDw=="
    },
    "keyId": 1
  },
  "registrationId": 161,
  "advSecretKey": "IcLeQ7Mxu08TGGMwPtv/diOBL5BezWwLPEqWRVUcBqQ=",
  "processedHistoryMessages": [
    {
      "key": {
        "remoteJid": "94766430185@s.whatsapp.net",
        "fromMe": true,
        "id": "01BD24E65C6D7CE870589B1BCDD2F616"
      },
      "messageTimestamp": 1754734433
    },
    {
      "key": {
        "remoteJid": "94766430185@s.whatsapp.net",
        "fromMe": true,
        "id": "332F1A6029719C2874AEA190EBB442E5"
      },
      "messageTimestamp": 1754734433
    },
    {
      "key": {
        "remoteJid": "94766430185@s.whatsapp.net",
        "fromMe": true,
        "id": "F5754EF56E66252CC4D52B6A31991323"
      },
      "messageTimestamp": 1754734446
    },
    {
      "key": {
        "remoteJid": "94766430185@s.whatsapp.net",
        "fromMe": true,
        "id": "26EEED602EFF92EECD5F60E004BA8533"
      },
      "messageTimestamp": 1754734452
    },
    {
      "key": {
        "remoteJid": "94766430185@s.whatsapp.net",
        "fromMe": true,
        "id": "0CF0BB0DC8DF4F8FCBDBBD3490969305"
      },
      "messageTimestamp": 1754734461
    },
    {
      "key": {
        "remoteJid": "94766430185@s.whatsapp.net",
        "fromMe": true,
        "id": "E1209054B5C325508484A984FB2C2E93"
      },
      "messageTimestamp": 1754734473
    },
    {
      "key": {
        "remoteJid": "94766430185@s.whatsapp.net",
        "fromMe": true,
        "id": "E0AC9EA9C5D8244554FAC66B05B428F1"
      },
      "messageTimestamp": 1754734478
    },
    {
      "key": {
        "remoteJid": "94766430185@s.whatsapp.net",
        "fromMe": true,
        "id": "B47E82E4112A5A6ACDB8A8D0BD14ED99"
      },
      "messageTimestamp": 1754734486
    },
    {
      "key": {
        "remoteJid": "94766430185@s.whatsapp.net",
        "fromMe": true,
        "id": "089EEC17199BB2AA9DDC4D7CE2F1E76B"
      },
      "messageTimestamp": 1754734493
    },
    {
      "key": {
        "remoteJid": "94766430185@s.whatsapp.net",
        "fromMe": true,
        "id": "D71FA85175705223ABAEAEFB5FE3FF29"
      },
      "messageTimestamp": 1754734494
    }
  ],
  "nextPreKeyId": 34,
  "firstUnuploadedPreKeyId": 34,
  "accountSyncCounter": 1,
  "accountSettings": {
    "unarchiveChats": false
  },
  "registered": true,
  "pairingCode": "AEBP8QKR",
  "me": {
    "id": "94766430185:48@s.whatsapp.net",
    "lid": "86690223935696:48@lid",
    "name": "👾"
  },
  "account": {
    "details": "CIPMyb4HENC+3MQGGAMgACgA",
    "accountSignatureKey": "q39xTse9kTGo2ec9ShcxBDP6d1TYQabAhdQ71sKcygQ=",
    "accountSignature": "v+TWv/2O4TQB7+wbQyPPa5LeyEHgTOPxtkERBcjWV8W66qxl2V/doac06llRSvWY48+wkp5uKGJmxX/WngGlDg==",
    "deviceSignature": "/AP10IsLs41A4FXIT2PYY5Qw0gBWe1Vgp+g8qCehWZ1ymVEqn4/+5sHCHrla/RbU2YjFgcSLiUizIraFRXrvCw=="
  },
  "signalIdentities": [
    {
      "identifier": {
        "name": "94766430185:48@s.whatsapp.net",
        "deviceId": 0
      },
      "identifierKey": {
        "type": "Buffer",
        "data": "Bat/cU7HvZExqNnnPUoXMQQz+ndU2EGmwIXUO9bCnMoE"
      }
    }
  ],
  "platform": "android",
  "routingInfo": {
    "type": "Buffer",
    "data": "CA0IBQ=="
  },
  "lastAccountSyncTimestamp": 1754734429,
  "lastPropHash": "PWk5B",
  "myAppStateKeyId": "AAAAABLq"
}