{
  "noiseKey": {
    "private": {
      "type": "Buffer",
      "data": "sOfoWFY9h+IIMSLCBEd/hVlFlCLixTgAGvlJIhkRY0I="
    },
    "public": {
      "type": "Buffer",
      "data": "+NnNZURS7L0jGdnk/GQbndq3m+lQT4bflKFDyZP/4DA="
    }
  },
  "pairingEphemeralKeyPair": {
    "private": {
      "type": "Buffer",
      "data": "WHl6hg0JSBHyBq8Mo4RzXx8V5u76dUXaMJI+POV832Y="
    },
    "public": {
      "type": "Buffer",
      "data": "nJeoeiaJeQGQARRMqAlfNVhVanNKZkIi9zD/MJP9OSA="
    }
  },
  "signedIdentityKey": {
    "private": {
      "type": "Buffer",
      "data": "aCGktXScjzrLAZSJ1FTIx9tWJSompzeqyj+d/cevKXc="
    },
    "public": {
      "type": "Buffer",
      "data": "hhJ5GsXfyaxpiC3iw8RkBkcIrfGQ9f7FrV36b4ytm0E="
    }
  },
  "signedPreKey": {
    "keyPair": {
      "private": {
        "type": "Buffer",
        "data": "UIYU7T7tczxvHpEJSyhRusYv3m6KMQ6JRg5zrvRgCm0="
      },
      "public": {
        "type": "Buffer",
        "data": "rA6ARFSqjCadEdfvaDEPv0CVhnykFTZkreKL64iTKTg="
      }
    },
    "signature": {
      "type": "Buffer",
      "data": "5VyPq8XMcu9LwJdxjvMTc7vEjTNdOdnRNciboXrbT6PppBvPpLLKxZvX/PU3ikNwwNcP1TdcuasfE+YHgVQCjA=="
    },
    "keyId": 1
  },
  "registrationId": 147,
  "advSecretKey": "KgIBkO7+u/WaE6emm7V89oz3kEa8E3M5sm1GYZcuG14=",
  "processedHistoryMessages": [],
  "nextPreKeyId": 41,
  "firstUnuploadedPreKeyId": 41,
  "accountSyncCounter": 0,
  "accountSettings": {
    "unarchiveChats": false
  },
  "registered": true,
  "pairingCode": "QKCLYQ3S",
  "me": {
    "id": "94755335072:63@s.whatsapp.net",
    "name": "𝘿\n\n𝙀\n\n𝙑\n\n\n𝙏\n\n𝙃\n\n𝙀\n\n𝙀\n\n𝙆\n\n𝙎\n\n𝙃\n\n𝘼\n\n𝙉\n\n𝘼",
    "lid": "174002513379475:63@lid"
  },
  "account": {
    "details": "COOBo/oGEPOtx8QGGAEgACgA",
    "accountSignatureKey": "jZh93JOzTQveStrWEoTba2QYI3cvKWeVhRdN9YOotFs=",
    "accountSignature": "FFFf2+YAdp4YG1BRnr58GtDIKD4EX4+UzOF4iG2e3TiYkpIAR6mxkP2EEYhGUvuJFhciobQe/U2YIVyrTmf6DQ==",
    "deviceSignature": "4lvd6xIywoutIhWyqnxoS7sH/HwVe920vrgv8cSMc7uX1n+1RDUgxA+76GDuV2dj8aS/Y+gfKflilWNyCme4gA=="
  },
  "signalIdentities": [
    {
      "identifier": {
        "name": "94755335072:63@s.whatsapp.net",
        "deviceId": 0
      },
      "identifierKey": {
        "type": "Buffer",
        "data": "BY2YfdyTs00L3kra1hKE22tkGCN3LylnlYUXTfWDqLRb"
      }
    }
  ],
  "platform": "smba",
  "routingInfo": {
    "type": "Buffer",
    "data": "CAIIBQ=="
  },
  "lastAccountSyncTimestamp": 1754388234,
  "lastPropHash": "PWk5B",
  "myAppStateKeyId": "AAAAAMiD"
}