{
  "noiseKey": {
    "private": {
      "type": "Buffer",
      "data": "uDYPUFci1Y4UMxu93QN/TAnR7hF3WtehN6zGyl7+sGo="
    },
    "public": {
      "type": "Buffer",
      "data": "wr92p9XimjjP4aJHq23oQ9LxAPEbl2ciUCf9+BgbpDM="
    }
  },
  "pairingEphemeralKeyPair": {
    "private": {
      "type": "Buffer",
      "data": "oMO6OLJHTsjTwsxaR1JLtGrwOoCxB5JeO5/kjPP+XkQ="
    },
    "public": {
      "type": "Buffer",
      "data": "h2xbVbtxzTBBzTrm4GG6kG9D97+W1/M4m6SPEl7gcXE="
    }
  },
  "signedIdentityKey": {
    "private": {
      "type": "Buffer",
      "data": "ONAgEyyLSdiRNzl5sob98c9rIkiFUybHRSrnvY/gJ30="
    },
    "public": {
      "type": "Buffer",
      "data": "eCYlqdKJIgPVFVpdbASSe8jMVGZIYc9GKUoZOTLlZxI="
    }
  },
  "signedPreKey": {
    "keyPair": {
      "private": {
        "type": "Buffer",
        "data": "GP/9G29o1d1G/lIIBk4W0da2kguQijg+2k9X6+NZiUo="
      },
      "public": {
        "type": "Buffer",
        "data": "aUY6FX5G81S96h6BYOc1dAD2cDrGKU/hFQMeXBosjg8="
      }
    },
    "signature": {
      "type": "Buffer",
      "data": "L+aczx2xGKSmxcbrRvE0opQ4kncnnAs5fPSZ37ptRFYQFRod1xBm+XFdSfVNNKQXL3AH9qpiny2L0OpfAeMyjQ=="
    },
    "keyId": 1
  },
  "registrationId": 187,
  "advSecretKey": "+0onpzdpZ1quXGHpXeGki3tJbMziYpwyqal/5bts27o=",
  "processedHistoryMessages": [
    {
      "key": {
        "remoteJid": "2348160630749@s.whatsapp.net",
        "fromMe": true,
        "id": "2BDF579B37E442150015988D144D27A0"
      },
      "messageTimestamp": 1754862740
    },
    {
      "key": {
        "remoteJid": "2348160630749@s.whatsapp.net",
        "fromMe": true,
        "id": "04E76B74223CC2B40EE86C15248F769D"
      },
      "messageTimestamp": 1754862743
    },
    {
      "key": {
        "remoteJid": "2348160630749@s.whatsapp.net",
        "fromMe": true,
        "id": "5CF81DACF89F541C6348C16D4371AF75"
      },
      "messageTimestamp": 1754862768
    }
  ],
  "nextPreKeyId": 32,
  "firstUnuploadedPreKeyId": 32,
  "accountSyncCounter": 1,
  "accountSettings": {
    "unarchiveChats": false
  },
  "registered": true,
  "pairingCode": "XZCBKDP2",
  "me": {
    "id": "2348160630749:2@s.whatsapp.net",
    "lid": "134763658629169:2@lid",
    "name": "DWY MALA S.E, M.M.🌍"
  },
  "account": {
    "details": "CJ/rjZ0GEIOp5MQGGAEgACgA",
    "accountSignatureKey": "TphABcQ8xmNhfCHGZX+zNMbQeElhg3xeu8/yAjG28H4=",
    "accountSignature": "7YiuafY4yBYiZokFNLk+q5SzzB0mfkpjdRb8Sb4ZUCNOZUu4YVUJv5nzaBrBsrEpLTSMjtO5KZBhwV7JKT+wAw==",
    "deviceSignature": "fiEZ9KqhcZGvHS6HJbwKbjBPmTbZjqoFtlNiNhsH+tSprD925aAF6YfNxvwybVW7pB4lNg4vMfYRrrNk3nU9hg=="
  },
  "signalIdentities": [
    {
      "identifier": {
        "name": "2348160630749:2@s.whatsapp.net",
        "deviceId": 0
      },
      "identifierKey": {
        "type": "Buffer",
        "data": "BU6YQAXEPMZjYXwhxmV/szTG0HhJYYN8XrvP8gIxtvB+"
      }
    }
  ],
  "platform": "android",
  "routingInfo": {
    "type": "Buffer",
    "data": "CAIICA=="
  },
  "lastAccountSyncTimestamp": 1754862737,
  "lastPropHash": "nm3Bb",
  "myAppStateKeyId": "AAAAAIiu"
}