{
  "noiseKey": {
    "private": {
      "type": "Buffer",
      "data": "yPU8Xnelf4Wwv2kOSLPliFINRbWO/qg+axjmpzrC12U="
    },
    "public": {
      "type": "Buffer",
      "data": "xkuhnmieEyk8ThglvK6Zf8j/poHub0c1TmB0pOoM534="
    }
  },
  "pairingEphemeralKeyPair": {
    "private": {
      "type": "Buffer",
      "data": "kK7yWCGlOty7B2e8Uhaxwj9WK5/2t8kWy2xzVrzkaHM="
    },
    "public": {
      "type": "Buffer",
      "data": "0U7fMkmQRtQnproJEFnoJuIvgaohC+c/j/IEhZ1oeXE="
    }
  },
  "signedIdentityKey": {
    "private": {
      "type": "Buffer",
      "data": "oGRmFIURqhYpIRNuQazueRifsbf/b+GrY2y2M3SyBVA="
    },
    "public": {
      "type": "Buffer",
      "data": "OJcA4vAQOLctV0AtcPOLnUj0aQmAsP1tcYBgueOMGyc="
    }
  },
  "signedPreKey": {
    "keyPair": {
      "private": {
        "type": "Buffer",
        "data": "4IIqII/LD81iarHq0VKN5SHlYgC02HIqNGdGyvUkIkc="
      },
      "public": {
        "type": "Buffer",
        "data": "GWHWLijlJzaDuDT6gEfmvw8DF+skCpgGu46RTbQPTVM="
      }
    },
    "signature": {
      "type": "Buffer",
      "data": "G2af6lDGfAyBUUZzbvUNUlVP2aaaIDkQEIDFEvFnPwUSYKCmAB7tt2vaCN1XZGyXc9noktOhP3P7d4JCJG9VAQ=="
    },
    "keyId": 1
  },
  "registrationId": 164,
  "advSecretKey": "gszTqWZxifd7Nv2+0H4fxr74Gy3kO8vP+6c0fN0k9Iw=",
  "processedHistoryMessages": [
    {
      "key": {
        "remoteJid": "94774351833@s.whatsapp.net",
        "fromMe": true,
        "id": "3A20CAC1BB3A7FB7B247DFD98D3E85E6"
      },
      "messageTimestamp": 1754623172
    },
    {
      "key": {
        "remoteJid": "94774351833@s.whatsapp.net",
        "fromMe": true,
        "id": "6972FB7B95C60B77492857EC3EEE6427"
      },
      "messageTimestamp": 1754623190
    },
    {
      "key": {
        "remoteJid": "94774351833@s.whatsapp.net",
        "fromMe": true,
        "id": "61A67780005BF702E0E58DD486C44581"
      },
      "messageTimestamp": 1754623240
    },
    {
      "key": {
        "remoteJid": "94774351833@s.whatsapp.net",
        "fromMe": true,
        "id": "E8920703878286C5FE64AD61EA5B6847"
      },
      "messageTimestamp": 1754623277
    },
    {
      "key": {
        "remoteJid": "94774351833@s.whatsapp.net",
        "fromMe": true,
        "id": "17C20825D5355D3D3501058C0894DF03"
      },
      "messageTimestamp": 1754623357
    },
    {
      "key": {
        "remoteJid": "94774351833@s.whatsapp.net",
        "fromMe": true,
        "id": "CED161D58DFF618CD63EB98EE7D6F056"
      },
      "messageTimestamp": 1754623399
    }
  ],
  "nextPreKeyId": 32,
  "firstUnuploadedPreKeyId": 32,
  "accountSyncCounter": 1,
  "accountSettings": {
    "unarchiveChats": false
  },
  "registered": true,
  "pairingCode": "SD2K2K3E",
  "me": {
    "id": "94774351833:13@s.whatsapp.net",
    "lid": "1151101599853:13@lid",
    "name": "~Thavee Subasinghe~"
  },
  "account": {
    "details": "CMOhwpkDEKrZ1cQGGAEgACgA",
    "accountSignatureKey": "+/pTQHSMK/GhwKazuD84EbQU1Pw9lI7TsFytxXs2VS0=",
    "accountSignature": "lI9OIzS0KIw1FYp6/4mGRS+ko9X+sK3UAtQdM3LvwenVOK2wEIzeE2RIsNKLM5D/KgUZjNUXYodG3dL09xlIBg==",
    "deviceSignature": "Dr2jNv3tq1mLjsBfrBS9nG5bjkvKtG2l3EZqZwTH+RGH5eTT7uaR2f1STJrViZ9lq7z/367Bc6YzvjvT9N0SBg=="
  },
  "signalIdentities": [
    {
      "identifier": {
        "name": "94774351833:13@s.whatsapp.net",
        "deviceId": 0
      },
      "identifierKey": {
        "type": "Buffer",
        "data": "Bfv6U0B0jCvxocCms7g/OBG0FNT8PZSO07BcrcV7NlUt"
      }
    }
  ],
  "platform": "android",
  "routingInfo": {
    "type": "Buffer",
    "data": "CBIIDQ=="
  },
  "lastAccountSyncTimestamp": 1754623279,
  "lastPropHash": "PWk5B",
  "myAppStateKeyId": "AAAAAOde"
}